ts/__init__.py
ts/auth.py
ts/client/__init.__.py
ts/client/asynchronous.py
ts/client/base.py
ts/client/synchronous.py
ts_api-0.2.3.dist-info/LICENSE
ts_api-0.2.3.dist-info/METADATA
ts_api-0.2.3.dist-info/WHEEL
ts_api-0.2.3.dist-info/RECORD
