Metadata-Version: 2.1
Name: ts-api
Version: 0.2.3
Summary: An unofficial wrapper for the TradeStation API.
Home-page: https://github.com/pattertj/ts-api
License: LICENSE
Keywords: tradestation,finance,trading,automated-trading,tradestation-api,ts-api
Author: Tyler Patterson
Author-email: pattertj@duck.com
Requires-Python: >=3.8.1,<4.0
Classifier: Development Status :: 3 - Alpha
Classifier: License :: OSI Approved :: MIT License
Classifier: License :: Other/Proprietary License
Classifier: Natural Language :: English
Classifier: Operating System :: OS Independent
Classifier: Programming Language :: Python
Classifier: Programming Language :: Python :: 3
Classifier: Programming Language :: Python :: 3.9
Classifier: Programming Language :: Python :: 3.10
Classifier: Programming Language :: Python :: 3.11
Classifier: Programming Language :: Python :: 3.0
Classifier: Programming Language :: Python :: 3.8
Classifier: Topic :: Office/Business :: Financial
Requires-Dist: httpx (>=0.24.0,<0.25.0)
Project-URL: Repository, https://github.com/pattertj/ts-api
